causaliq_data/__init__.py
causaliq_data/cli.py
causaliq_data/data.py
causaliq_data/indep.py
causaliq_data/numpy.py
causaliq_data/oracle.py
causaliq_data/pandas.py
causaliq_data/preprocess.py
causaliq_data/py.typed
causaliq_data/score.py
causaliq_data-0.3.0.dist-info/licenses/LICENSE
causaliq_data-0.3.0.dist-info/METADATA
causaliq_data-0.3.0.dist-info/WHEEL
causaliq_data-0.3.0.dist-info/entry_points.txt
causaliq_data-0.3.0.dist-info/top_level.txt
causaliq_data-0.3.0.dist-info/RECORD
