Metadata-Version: 2.4
Name: causaliq-data
Version: 0.3.0
Summary: Data caching, scoring and testing for causal discovery
Author-email: CausalIQ <info@causaliq.com>
Maintainer-email: CausalIQ <info@causaliq.com>
License: MIT
Project-URL: Homepage, https://github.com/causaliq/causaliq-data
Project-URL: Documentation, https://github.com/causaliq/causaliq-data#readme
Project-URL: Repository, https://github.com/causaliq/causaliq-data
Project-URL: Bug Tracker, https://github.com/causaliq/causaliq-data/issues
Keywords: causaliq
Classifier: Development Status :: 2 - Pre-Alpha
Classifier: Intended Audience :: Science/Research
Classifier: License :: OSI Approved :: MIT License
Classifier: Operating System :: OS Independent
Classifier: Programming Language :: Python :: 3
Classifier: Programming Language :: Python :: 3.9
Classifier: Programming Language :: Python :: 3.10
Classifier: Programming Language :: Python :: 3.11
Classifier: Programming Language :: Python :: 3.12
Classifier: Topic :: Scientific/Engineering
Classifier: Topic :: Software Development :: Libraries :: Python Modules
Requires-Python: >=3.9
License-File: LICENSE
Requires-Dist: click>=8.0.0
Requires-Dist: pandas>=1.3.0
Requires-Dist: numpy>=1.21.0
Requires-Dist: scipy>=1.7.0
Requires-Dist: StrEnum>=0.4.15
Requires-Dist: causaliq-core>=0.3.0
Provides-Extra: dev
Requires-Dist: pytest>=7.0.0; extra == "dev"
Requires-Dist: pytest-cov>=4.0.0; extra == "dev"
Requires-Dist: pytest-mock>=3.10.0; extra == "dev"
Requires-Dist: black>=22.0.0; extra == "dev"
Requires-Dist: isort>=5.10.0; extra == "dev"
Requires-Dist: flake8>=5.0.0; extra == "dev"
Requires-Dist: mypy>=1.0.0; extra == "dev"
Requires-Dist: types-requests>=2.32.0; extra == "dev"
Requires-Dist: pandas-stubs>=2.0.0; extra == "dev"
Requires-Dist: scipy-stubs>=1.10.0; python_version >= "3.10" and extra == "dev"
Requires-Dist: pre-commit>=2.20.0; extra == "dev"
Requires-Dist: build>=0.8.0; extra == "dev"
Requires-Dist: twine>=4.0.0; extra == "dev"
Provides-Extra: test
Requires-Dist: pytest>=7.0.0; extra == "test"
Requires-Dist: pytest-cov>=4.0.0; extra == "test"
Requires-Dist: pytest-mock>=3.10.0; extra == "test"
Provides-Extra: docs
Requires-Dist: mkdocs>=1.5.0; extra == "docs"
Requires-Dist: mkdocs-material>=9.0.0; extra == "docs"
Requires-Dist: mkdocstrings==0.30.1; extra == "docs"
Requires-Dist: mkdocstrings-python==1.18.2; extra == "docs"
Dynamic: license-file
